<?xml version="1.0" encoding="UTF-8"?>
<objects serializationModel="Studio.02.01.00">
	<object class="AudioFile" id="{1cc858a3-132a-4d73-a1ab-59a2f07f0934}">
		<property name="assetPath">
			<value>SchiavoNobileM3_Edoardo.mp3</value>
		</property>
		<property name="frequencyInKHz">
			<value>44.0999985</value>
		</property>
		<property name="channelCount">
			<value>2</value>
		</property>
		<property name="length">
			<value>2.7167346938775512</value>
		</property>
		<relationship name="masterAssetFolder">
			<destination>{a24f8706-08d9-489f-9240-326fc771a170}</destination>
		</relationship>
	</object>
</objects>
